emr_launcher/__init__.py
emr_launcher/launcher.py
emr_launcher/template_functions.py
emr_launcher-1.1.1.data/scripts/emr_launcher
emr_launcher-1.1.1.dist-info/DESCRIPTION.rst
emr_launcher-1.1.1.dist-info/METADATA
emr_launcher-1.1.1.dist-info/RECORD
emr_launcher-1.1.1.dist-info/WHEEL
emr_launcher-1.1.1.dist-info/metadata.json
emr_launcher-1.1.1.dist-info/top_level.txt
