Metadata-Version: 2.0
Name: emr-launcher
Version: 1.1.1
Summary: Launches an AWS Elastic MapReduce cluster using templated configuration files written in JSON. Meant to make deployments consistent and reproducable.
Home-page: https://github.com/tuneinc/emr_launcher
Author: Nick Rushton
Author-email: nick@tune.com
License: MIT
Platform: UNKNOWN
Classifier: License :: OSI Approved :: MIT License
Classifier: Programming Language :: Python
Classifier: Programming Language :: Python :: 2.7
Classifier: Programming Language :: Python :: 3
Classifier: Programming Language :: Python :: 3.6
Classifier: Programming Language :: Python :: Implementation :: CPython
Classifier: Programming Language :: Python :: Implementation :: PyPy
Requires-Python: >=2.7.0
Requires-Dist: blessings (==1.6.1)
Requires-Dist: boto3 (==1.4.4)
Requires-Dist: jinja2
Requires-Dist: pytz (==2017.3)
